ob_dj_hubspot/apis/__init__.py
ob_dj_hubspot/apis/hubspot/__init__.py
ob_dj_hubspot/apis/hubspot/urls.py
ob_dj_hubspot/apis/hubspot/utils.py
ob_dj_hubspot/apis/hubspot/views.py
ob_dj_hubspot/core/__init__.py
ob_dj_hubspot/core/hubspot/__init__.py
ob_dj_hubspot/core/hubspot/apps.py
ob_dj_hubspot/core/hubspot/managers.py
ob_dj_hubspot/core/hubspot/models.py
ob_dj_hubspot/core/hubspot/settings_validation.py
ob_dj_hubspot/core/hubspot/tasks.py
ob_dj_hubspot/core/hubspot/urls.py
ob_dj_hubspot/core/hubspot/utils.py
ob_dj_hubspot/core/hubspot/views.py
ob_dj_hubspot/core/hubspot/admin/__init__.py
ob_dj_hubspot/core/hubspot/migrations/0001_initial.py
ob_dj_hubspot/core/hubspot/migrations/0002_hsoauth_stale.py
ob_dj_hubspot/core/hubspot/migrations/__init__.py
ob_dj_hubspot/core/hubspot/templates/admin_oauth_change_list.html
ob_dj_hubspot-0.0.9.dist-info/METADATA
ob_dj_hubspot-0.0.9.dist-info/WHEEL
ob_dj_hubspot-0.0.9.dist-info/top_level.txt
ob_dj_hubspot-0.0.9.dist-info/RECORD
